ghost/__init__.py
ghost/abs_resources.py
ghost/client.py
ghost/exceptions.py
ghost/resources.py
ghost/results.py
edwh_ghost-0.1.10.dist-info/METADATA
edwh_ghost-0.1.10.dist-info/WHEEL
edwh_ghost-0.1.10.dist-info/top_level.txt
edwh_ghost-0.1.10.dist-info/RECORD
