Metadata-Version: 2.1
Name: edwh-ghost
Version: 0.1.10
Summary: Python client for Ghost API v3/v4/v5
Home-page: https://github.com/educationwarehouse/edwh-ghost
Author: Education Warehouse
Author-email: remco.b@educationwarehouse.nl
License: MIT
Requires-Python: >=3.7
Requires-Dist: PyJWT >=2.4.0
Requires-Dist: requests
Requires-Dist: yarl
Provides-Extra: dev
Requires-Dist: black ; extra == 'dev'
Requires-Dist: pytest ; extra == 'dev'
Requires-Dist: coverage ; extra == 'dev'
Requires-Dist: Faker ; extra == 'dev'
Requires-Dist: python-dotenv ; extra == 'dev'
Requires-Dist: twine ; extra == 'dev'
Requires-Dist: build ; extra == 'dev'
